README.md
pyproject.toml
setup.cfg
setup.py
baseapp_payments/__init__.py
baseapp_payments.egg-info/PKG-INFO
baseapp_payments.egg-info/SOURCES.txt
baseapp_payments.egg-info/dependency_links.txt
baseapp_payments.egg-info/top_level.txt